bobbie-0.1.7.dist-info/METADATA
bobbie-0.1.7.dist-info/WHEEL
bobbie-0.1.7.dist-info/entry_points.txt
bobbie-0.1.7.dist-info/licenses/LICENSE
bobbie/__init__.py
bobbie/base.py
bobbie/options.py
bobbie/utilities.py
bobbie-0.1.7.dist-info/RECORD
