Metadata-Version: 2.1
Name: bobbie
Version: 0.1.7
Summary: Flexible, easy Python project configuration
Author-Email: Corey Rayburn Yung <coreyrayburnyung@gmail.com>
License: Apache Software License 2.0
Classifier: Development Status :: 4 - Beta
Classifier: Environment :: Console
Classifier: Intended Audience :: Developers
Classifier: Intended Audience :: Education
Classifier: License :: OSI Approved :: Apache Software License
Classifier: Programming Language :: Python
Classifier: Programming Language :: Python :: 3
Classifier: Programming Language :: Python :: 3 :: Only
Classifier: Programming Language :: Python :: 3.11
Classifier: Programming Language :: Python :: 3.12
Classifier: Programming Language :: Python :: 3.13
Classifier: Topic :: Software Development
Project-URL: Documentation, https://WithPrecedent.github.io/bobbie
Project-URL: Repository, https://github.com/WithPrecedent/bobbie
Project-URL: Issues, https://github.com/WithPrecedent/bobbie/issues
Project-URL: Changelog, https://WithPrecedent.github.io/bobbie/changelog
Requires-Python: >=3.11
Requires-Dist: bunches>=0.1.3
Requires-Dist: wonka>=0.1.4
Provides-Extra: env
Requires-Dist: python-dotenv; extra == "env"
Provides-Extra: xml
Requires-Dist: xmltodict; extra == "xml"
Provides-Extra: yaml
Requires-Dist: pyyaml; extra == "yaml"
